fluentcms_pager/__init__.py
fluentcms_pager/content_plugins.py
fluentcms_pager/models.py
fluentcms_pager/locale/nl/LC_MESSAGES/django.mo
fluentcms_pager/locale/nl/LC_MESSAGES/django.po
fluentcms_pager/migrations/0001_initial.py
fluentcms_pager/migrations/__init__.py
fluentcms_pager/static/admin/fluentcms_pager/pageradmin.js
fluentcms_pager/templates/fluentcms_pager/pager.html
fluentcms_pager/tests/__init__.py
fluentcms_pager/tests/models.py
fluentcms_pager/tests/test_page.py
fluentcms_pager/tests/migrations/0001_initial.py
fluentcms_pager/tests/migrations/__init__.py
fluentcms_pager-3.0.dist-info/AUTHORS
fluentcms_pager-3.0.dist-info/LICENSE
fluentcms_pager-3.0.dist-info/METADATA
fluentcms_pager-3.0.dist-info/WHEEL
fluentcms_pager-3.0.dist-info/top_level.txt
fluentcms_pager-3.0.dist-info/RECORD
